binaryformation/__init__.py
binaryformation-0.0.dist-info/METADATA
binaryformation-0.0.dist-info/WHEEL
binaryformation-0.0.dist-info/top_level.txt
binaryformation-0.0.dist-info/RECORD
