Metadata-Version: 2.1
Name: binaryformation
Version: 0.0
Summary: Can be used for conversion of binary
Home-page: UNKNOWN
Author: Saksham jain
License: UNKNOWN
Platform: UNKNOWN
